auto_init/__init__.py
auto_init/safe_context.py
auto_init-0.0.5.dist-info/METADATA
auto_init-0.0.5.dist-info/WHEEL
auto_init-0.0.5.dist-info/top_level.txt
auto_init-0.0.5.dist-info/RECORD
