Metadata-Version: 2.1
Name: auto-init
Version: 0.0.5
Summary: Dependency injection thanks to type hints in Python 3.6+
Home-page: https://github.com/jbasko/auto-init
Author: Jazeps Basko
Author-email: jazeps.basko@gmail.com
Maintainer: Jazeps Basko
Maintainer-email: jazeps.basko@gmail.com
License: MIT
Keywords: dependency injection type hinting typing
Platform: UNKNOWN
Classifier: Development Status :: 4 - Beta
Classifier: Intended Audience :: Developers
Classifier: Topic :: Software Development :: Libraries
Classifier: Programming Language :: Python
Classifier: Programming Language :: Python :: 3
Classifier: Programming Language :: Python :: 3.6
Classifier: Programming Language :: Python :: 3.7
Classifier: License :: OSI Approved :: MIT License
Requires-Python: >=3.6.0
Requires-Dist: dataclasses; python_version=="3.6"
Requires-Dist: contextvars; python_version=="3.6"
